manga_dl/__init__.py
manga_dl/entities/Chapter.py
manga_dl/entities/__init__.py
manga_dl/scrapers/Scraper.py
manga_dl/scrapers/__init__.py
manga_dl/scrapers/mangadex.py
manga_dl/test/__init__.py
manga_dl-0.3.1.data/scripts/manga-dl
manga_dl-0.3.1.dist-info/LICENSE
manga_dl-0.3.1.dist-info/METADATA
manga_dl-0.3.1.dist-info/WHEEL
manga_dl-0.3.1.dist-info/top_level.txt
manga_dl-0.3.1.dist-info/RECORD
