Metadata-Version: 2.1
Name: manga-dl
Version: 0.3.1
Summary: A Manga Downloader
Home-page: https://gitlab.namibsun.net/namibsun/python/manga-dl
Author: Hermann Krumrey
Author-email: hermann@krumreyh.com
License: GNU GPL3
Platform: UNKNOWN
Classifier: License :: OSI Approved :: GNU General Public License v3 (GPLv3)
Requires-Dist: bs4
Requires-Dist: requests
Requires-Dist: sentry-sdk
Requires-Dist: puffotter
Requires-Dist: cfscrape
